zippathlib/__init__.py
zippathlib/__main__.py
zippathlib/zip_pathlib.py
zippathlib-0.6.0.dist-info/licenses/LICENSE
zippathlib-0.6.0.dist-info/METADATA
zippathlib-0.6.0.dist-info/WHEEL
zippathlib-0.6.0.dist-info/entry_points.txt
zippathlib-0.6.0.dist-info/top_level.txt
zippathlib-0.6.0.dist-info/RECORD
