Metadata-Version: 2.4
Name: zippathlib
Version: 0.6.0
Summary: A `pathlib.Path`-like class for accessing the contents of ZIP archives
Author-email: Paul McGuire <ptmcg_pm+zippathlib@gmail.com>
License-Expression: MIT
Project-URL: Homepage, https://github.com/ptmcg/zippathlib
Project-URL: Source, https://github.com/ptmcg/zippathlib.git
Classifier: Development Status :: 4 - Beta
Classifier: Intended Audience :: Developers
Classifier: Intended Audience :: Information Technology
Classifier: Operating System :: OS Independent
Classifier: Programming Language :: Python
Classifier: Programming Language :: Python :: 3
Classifier: Programming Language :: Python :: 3.12
Classifier: Programming Language :: Python :: 3.13
Classifier: Programming Language :: Python :: 3.14
Classifier: Programming Language :: Python :: 3 :: Only
Classifier: Programming Language :: Python :: Free Threading :: 3 - Stable
Classifier: Topic :: System :: Archiving
Classifier: Topic :: System :: Archiving :: Compression
Classifier: Topic :: System :: Filesystems
Classifier: Topic :: Utilities
Classifier: Typing :: Typed
Requires-Python: >=3.12
License-File: LICENSE
Requires-Dist: rich>=9.7.0
Dynamic: license-file
